iTransformer/__init__.py
iTransformer/attend.py
iTransformer/iTransformer.py
iTransformer/iTransformer2D.py
iTransformer/iTransformerFFT.py
iTransformer/revin.py
itransformer-0.8.1.dist-info/licenses/LICENSE
itransformer-0.8.1.dist-info/METADATA
itransformer-0.8.1.dist-info/WHEEL
itransformer-0.8.1.dist-info/top_level.txt
itransformer-0.8.1.dist-info/RECORD
