Metadata-Version: 2.4
Name: iTransformer
Version: 0.8.1
Summary: iTransformer - Inverted Transformer Are Effective for Time Series Forecasting
Home-page: https://github.com/lucidrains/iTransformer
Author: Phil Wang
Author-email: lucidrains@gmail.com
License: MIT
Keywords: artificial intelligence,deep learning,transformers,attention mechanism,time series forecasting
Classifier: Development Status :: 4 - Beta
Classifier: Intended Audience :: Developers
Classifier: Topic :: Scientific/Engineering :: Artificial Intelligence
Classifier: License :: OSI Approved :: MIT License
Classifier: Programming Language :: Python :: 3.6
License-File: LICENSE
Requires-Dist: beartype
Requires-Dist: einops>=0.8.0
Requires-Dist: hyper-connections>=0.0.14
Requires-Dist: gateloop-transformer>=0.2.3
Requires-Dist: rotary-embedding-torch
Requires-Dist: torch>=2.3
Dynamic: author
Dynamic: author-email
Dynamic: classifier
Dynamic: description-content-type
Dynamic: home-page
Dynamic: keywords
Dynamic: license
Dynamic: license-file
Dynamic: requires-dist
Dynamic: summary
